ai_code_summary/__init__.py
ai_code_summary/env_variables.py
ai_code_summary/ai/__init__.py
ai_code_summary/ai/summary.py
ai_code_summary/ai/summary_test.py
ai_code_summary/code/__init__.py
ai_code_summary/code/gitignore_pathspec.py
ai_code_summary/code/gitignore_pathspec_test.py
ai_code_summary/files/__init__.py
ai_code_summary/files/file_manager.py
ai_code_summary/files/file_manager_test.py
ai_code_summary/markdown/__init__.py
ai_code_summary/markdown/export.py
ai_code_summary/markdown/export_test.py
ai_code_summary-0.1.3.dist-info/METADATA
ai_code_summary-0.1.3.dist-info/WHEEL
ai_code_summary-0.1.3.dist-info/licenses/LICENSE
ai_code_summary-0.1.3.dist-info/RECORD
