Metadata-Version: 2.3
Name: ai-code-summary
Version: 0.1.3
Summary: This project automates the process of aggregating code files from a directory into a single markdown file, ready for use in an OpenAI Assistant or any RAG model. It intelligently skips files specified in the .gitignore and leverages ChatGPT to generate concise summaries for each code file, ensuring that the final markdown file is both comprehensive and easy to understand.
Project-URL: repository, https://github.com/DEV3L/ai-code-summary
Author-email: Justin Beall <jus.beall@gmail.com>
License: /*
License-File: LICENSE
Keywords: AI,API,artificial intelligence,automation,code summary,data science,openai,python
Classifier: Development Status :: 4 - Beta
Classifier: Intended Audience :: Developers
Classifier: License :: OSI Approved :: MIT License
Classifier: Programming Language :: Python :: 3
Classifier: Programming Language :: Python :: 3.11
Classifier: Topic :: Software Development :: Libraries :: Python Modules
Requires-Python: >=3.11
Requires-Dist: loguru
Requires-Dist: openai
Requires-Dist: pathspec
Requires-Dist: python-dotenv
Requires-Dist: twine
